MANIFEST.in
README.md
setup.py
miquido_infra_spawner/GitlabService.py
miquido_infra_spawner/InfraSpawner.py
miquido_infra_spawner/__init__.py
miquido_infra_spawner/__main__.py
miquido_infra_spawner/config.yaml
miquido_infra_spawner.egg-info/PKG-INFO
miquido_infra_spawner.egg-info/SOURCES.txt
miquido_infra_spawner.egg-info/dependency_links.txt
miquido_infra_spawner.egg-info/not-zip-safe
miquido_infra_spawner.egg-info/requires.txt
miquido_infra_spawner.egg-info/top_level.txt
miquido_infra_spawner/template/.gitignore
miquido_infra_spawner/template/.gitlab-ci.yml
miquido_infra_spawner/template/app/acm.tf
miquido_infra_spawner/template/app/alb.tf
miquido_infra_spawner/template/app/cicd-docker.tf
miquido_infra_spawner/template/app/cicd.tf
miquido_infra_spawner/template/app/ecs-service.tf
miquido_infra_spawner/template/app/ecs.tf
miquido_infra_spawner/template/app/exec-role.tf
miquido_infra_spawner/template/app/gitlab-service.tf
miquido_infra_spawner/template/app/gitlab.tf
miquido_infra_spawner/template/app/ifology.tf
miquido_infra_spawner/template/app/route.tf
miquido_infra_spawner/template/app/sns.tf
miquido_infra_spawner/template/app/ssm.tf
miquido_infra_spawner/template/app/variables.tf
miquido_infra_spawner/template/app/versions.tf
miquido_infra_spawner/template/app/vpc.tf
miquido_infra_spawner/template/env/app-full.tf
miquido_infra_spawner/template/env/app.tf
miquido_infra_spawner/template/env/data.tf
miquido_infra_spawner/template/env/provider.tf
miquido_infra_spawner/template/env/state.tf
miquido_infra_spawner/template/env/variables.tf