Metadata-Version: 2.1
Name: miquido-infra-spawner
Version: 0.0.30
Summary: This project is meant to automate creation of new terraform repositories. Running the script will create a git repo in miquidos gitlab and start the pipeline deploying new environment
Home-page: UNKNOWN
Author: Marek
Author-email: marek.moscichowski@miquido.com
License: MIT
Platform: UNKNOWN
